<?xml version="1.0" encoding="UTF-8" standalone="yes"?>
 <items>

<item>
<title>[B]Guerra Civil (2024)[/B]</title>
<link>plugin://plugin.video.elementum/play?uri=magnet:?xt=urn:btih:90E50CA1D171B207523AB4999BA3644EF4AD33FD</link>
<thumbnail>https://www.themoviedb.org/t/p/w600_and_h900_bestv2/3Use5sOQWXL3BvcaKqUH7eQ7I53.jpg</thumbnail>
<fanart>https://media.themoviedb.org/t/p/w1920_and_h800_multi_faces/uv2twFGMk2qBdyJBJAVcrpRtSa9.jpg</fanart>
<info>Em um futuro não tão distante, quando uma guerra civil se instaura nos Estados Unidos, uma equipe pioneira de jornalistas de guerra viaja pelo país para registrar a dimensão e a situação de um cenário violento que tomou as ruas em uma rápida escalada, envolvendo toda a nação. No entanto, o trabalho de registro se transforma em uma guerra de sobrevivência quando eles também se tornam o alvo.</info>
</item>

</items>
